authz/__init__.py
authz/admin.py
authz/apps.py
authz/base.py
authz/decorators.py
authz/drf_permissions.py
authz/engine.py
authz/exceptions.py
authz/mixins.py
authz/models.py
authz/mutations.py
authz/policies.py
authz/queries.py
authz/schema.py
authz/services.py
authz/tests.py
authz/tests_graphql.py
authz/utils.py
authz/views.py
authz/dto/__init__.py
authz/dto/types.py
authz/dto_builders/__init__.py
authz/dto_builders/main.py
authz/management/__init__.py
authz/management/commands/__init__.py
authz/management/commands/seed_rbac.py
authz/migrations/0001_initial.py
authz/migrations/__init__.py
authz/templatetags/__init__.py
authz/templatetags/authz_tags.py
tarxemo_django_authz-0.2.2.dist-info/licenses/LICENSE
tarxemo_django_authz-0.2.2.dist-info/METADATA
tarxemo_django_authz-0.2.2.dist-info/WHEEL
tarxemo_django_authz-0.2.2.dist-info/top_level.txt
tarxemo_django_authz-0.2.2.dist-info/RECORD
