Metadata-Version: 2.4
Name: tarxemo-django-authz
Version: 0.2.2
Summary: A comprehensive, reusable Django authorization framework supporting RBAC and PBAC
Home-page: https://github.com/tarxemo/tarxemo-django-authz
Author: TarXemo
Project-URL: Homepage, https://github.com/tarxemo/tarxemo-django-authz
Project-URL: Bug Tracker, https://github.com/tarxemo/tarxemo-django-authz/issues
Classifier: Framework :: Django
Classifier: Programming Language :: Python :: 3
Classifier: License :: OSI Approved :: MIT License
Classifier: Operating System :: OS Independent
Requires-Python: >=3.8
License-File: LICENSE
Requires-Dist: Django
Requires-Dist: graphene-django
Requires-Dist: tarxemo-django-graphene-utils
Provides-Extra: drf
Requires-Dist: djangorestframework; extra == "drf"
Dynamic: home-page
Dynamic: license-file
Dynamic: requires-python
